diffusion_kinetics/__init__.py
diffusion_kinetics/cli.py
diffusion_kinetics/optimization/__init__.py
diffusion_kinetics/optimization/conHe_Param.py
diffusion_kinetics/optimization/dataset.py
diffusion_kinetics/optimization/diffusion_objective.py
diffusion_kinetics/optimization/diffusion_optimizer.py
diffusion_kinetics/optimization/forward_model_kinetics.py
diffusion_kinetics/pipeline/__init__.py
diffusion_kinetics/pipeline/base_pipeline.py
diffusion_kinetics/pipeline/multi_pipeline.py
diffusion_kinetics/pipeline/pipeline_config.py
diffusion_kinetics/pipeline/pipeline_output.py
diffusion_kinetics/pipeline/single_pipeline.py
diffusion_kinetics/preprocessing/calculate_experimental_results.py
diffusion_kinetics/preprocessing/generate_inputs.py
diffusion_kinetics/utils/kinetics_dataframe.py
diffusion_kinetics/utils/organize_x.py
diffusion_kinetics/utils/plot_results.py
diffusion_modeler-0.1.0.dist-info/METADATA
diffusion_modeler-0.1.0.dist-info/WHEEL
diffusion_modeler-0.1.0.dist-info/entry_points.txt
diffusion_modeler-0.1.0.dist-info/top_level.txt
diffusion_modeler-0.1.0.dist-info/RECORD
